location_local/__init__.py
location_local/city.py
location_local/city_ml.py
location_local/country.py
location_local/country_ml.py
location_local/county.py
location_local/county_ml.py
location_local/location_local_constants.py
location_local/locations_local_crud.py
location_local/neighborhood.py
location_local/neighborhood_ml.py
location_local/region.py
location_local/region_ml.py
location_local/state.py
location_local/state_ml.py
location_local/util.py
location_local-0.0.132.dist-info/METADATA
location_local-0.0.132.dist-info/WHEEL
location_local-0.0.132.dist-info/top_level.txt
location_local-0.0.132.dist-info/RECORD
