Metadata-Version: 2.4
Name: location-local
Version: 0.0.132
Summary: Location Local PyPI Package
Home-page: https://github.com/circles-zone/location-local-python-package
Author: Circles
Author-email: info@circles.ai
Classifier: Programming Language :: Python :: 3
Classifier: License :: Other/Proprietary License
Classifier: Operating System :: OS Independent
Requires-Dist: opencage>=2.3.0
Requires-Dist: phonenumbers>=8.13.35
Requires-Dist: database-mysql-local>=0.0.294
Requires-Dist: database-infrastructure-local>=0.0.23
Requires-Dist: logger-local>=0.0.59
Requires-Dist: language-remote>=0.0.13
Requires-Dist: python-sdk-remote>=0.0.93
Requires-Dist: user-context-remote>=0.0.4
Dynamic: author
Dynamic: author-email
Dynamic: classifier
Dynamic: description
Dynamic: description-content-type
Dynamic: home-page
Dynamic: requires-dist
Dynamic: summary
